[
    {
        "title": "Bloomify",
        "image": "../assets/react.svg",
        "link": "https://bl00mify.netlify.app/",
        "tech": ["JavaScript", "HTML", "CSS", "React", "Ant Design"]
    },
    {
        "title": "Solar System",
        "image": "../assets/react.svg",
        "link": "https://google.com",
        "tech": ["Java"]
    },
    {
        "title": "Minesweeper",
        "image": "../assets/react.svg",
        "link": "https://google.com",
        "tech": ["Java"]
    },
    {
        "title": "Ping Calculator",
        "image": "../assets/react.svg",
        "link": "https://google.com",
        "tech": ["Python"]
    },
    {
        "title": "Password Generator",
        "image": "../assets/react.svg",
        "link": "https://google.com",
        "tech": ["Python"]
    },
    {
        "title": "Solar System",
        "image": "../assets/react.svg",
        "link": "https://google.com",
        "tech": ["Java"]
    }
]